react_stats/__init__.py
react_stats/ahoy.py
react_stats/assets.json
react_stats/auto_assets.py
react_stats/exts.py
react_stats/get_stats.py
react_stats/languages.json
react_stats/make_assets.py
react_stats-0.86.dist-info/METADATA
react_stats-0.86.dist-info/WHEEL
react_stats-0.86.dist-info/entry_points.txt
react_stats-0.86.dist-info/top_level.txt
react_stats-0.86.dist-info/RECORD
