Metadata-Version: 2.1
Name: react-stats
Version: 0.86
Summary: UNKNOWN
Home-page: UNKNOWN
License: UNKNOWN
Platform: UNKNOWN
Requires-Dist: tabulate
Requires-Dist: chardet
Requires-Dist: pandas
Requires-Dist: asciibars
Requires-Dist: watchdog
